UseData: true
BuildSelection: Cycle
MinGamesWinrateBased: 5
BuildChoices:
  Protoss:
    BotName: SC2Agent_vProtoss
    Cycle:
    - TvP
  Terran:
    BotName: SC2Agent_vTerran
    Cycle:
    - TvT
  Zerg:
    BotName: SC2Agent_vZerg
    Cycle:
    - TvZ
  Random:
    BotName: SC2Agent_vRandom
    Cycle:
    - TvZ
Builds:
  TvZ:
    AutoSupplyAtSupply: 0
    ConstantWorkerProductionTill: 66
    OpeningBuildOrder:
    - 14 supply
    - 16 barracks
    - 16 gas
    - 19 reaper
    - 19 orbital
    - 20 expand
    - 21 factory
    - 22 supply
    - 23 hellion x2
    - 24 gas
    - 26 barrackstechlab
    - 28 stimpack
    - 28 barracks
    - 30 engineeringbay
    - 32 starport
    - 32 terraninfantryweaponslevel1
    - 34 marauder x2
    - 34 starportreactor
    - 36 barracks
    - 36 medivac x2
    - 38 shieldwall
    - 42 supply
    - 46 marine x4
    - 52 factory
    - 56 widowmine x2
    - 60 commandcenter
    - 64 terraninfantryarmorslevel1
  TvP:
    AutoSupplyAtSupply: 0
    ConstantWorkerProductionTill: 70
    OpeningBuildOrder:
    - 14 supply
    - 16 barracks
    - 16 gas
    - 19 expand
    - 20 reaper
    - 20 orbital
    - 21 factory
    - 22 gas
    - 23 supply
    - 23 starport
    - 24 marine
    - 25 barrackstechlab
    - 25 starportreactor
    - 28 stimpack
    - 29 orbital
    - 30 bunker
    - 32 factorytechlab
    - 34 engineeringbay
    - 36 supply
    - 38 siegetank
    - 42 shieldwall
    - 44 barracks
    - 46 medivac x2
    - 50 siegetank
    - 52 terraninfantryweaponslevel1
    - 56 barracks
    - 60 expand
    - 64 supply x2
    - 66 barrackstechlab
    - 68 punishergrenades
    - 72 armory
    - 76 vikingfighter x2
    - 80 terraninfantryarmorslevel1
    - 84 engineeringbay
    - 88 orbital
    - 94 starport
    - 100 terraninfantryweaponslevel2
    - 102 terraninfantryarmorslevel2
    - 110 expand
    - 120 ghostacademy
  TvT:
    AutoSupplyAtSupply: 0
    ConstantWorkerProductionTill: 66
    OpeningBuildOrder:
    - 14 supply
    - 16 barracks
    - 16 gas
    - 19 orbital
    - 19 reaper
    - 20 expand
    - 21 marine
    - 22 factory
    - 23 gas
    - 24 supply
    - 24 starport
    - 24 barracksreactor
    - 26 bunker
    - 26 starportreactor
    - 30 factorytechlab
    - 32 siegetank
    - 34 orbital
    - 35 supply
    - 40 engineeringbay
    - 42 medivac
    - 44 barracks
    - 46 siegetank
    - 48 barrackstechlab
    - 50 supply
    - 52 stimpack
    - 54 missileturret
    - 58 siegetank
    - 62 terraninfantryweaponslevel1
    - 66 supply
    - 68 shieldwall
    - 72 medivac
    - 76 barracks
    - 80 expand
    - 84 engineeringbay
    - 88 terraninfantryarmorslevel1
    - 92 armory
    - 100 terraninfantryweaponslevel2
    - 110 terraninfantryarmorslevel2
    notes:
    - 'SKIPPED non-researchable / unsupported step: research SiegeTech'
